dsioutilities/__init__.py
dsioutilities/dataset.py
dsioutilities/utils.py
dsioutilities/object/__init__.py
dsioutilities/object/filesystem.py
dsioutilities/object/minio.py
dsioutilities/object/object.py
dsioutilities/tabular/__init__.py
dsioutilities/tabular/filesystem.py
dsioutilities/tabular/hive.py
dsioutilities/tabular/minio.py
dsioutilities/tabular/tabular.py
ds_io_utilities-0.0.31.dist-info/METADATA
ds_io_utilities-0.0.31.dist-info/WHEEL
ds_io_utilities-0.0.31.dist-info/top_level.txt
ds_io_utilities-0.0.31.dist-info/RECORD
