Metadata-Version: 2.1
Name: ds-io-utilities
Version: 0.0.31
Summary: Utils for datasets IO operations in Alida.
Home-page: UNKNOWN
Author: Alida research team
Author-email: engineering-alida-lab@eng.it
License: UNKNOWN
Platform: UNKNOWN
Classifier: Programming Language :: Python :: 3
Classifier: License :: OSI Approved :: MIT License
Classifier: Operating System :: OS Independent
Requires-Python: >=3.6
Requires-Dist: bda-service-utils
Requires-Dist: s3fs
Requires-Dist: minio
Requires-Dist: alida-arg-parser
Requires-Dist: boto
